Metrik/__init__.py
Metrik/fast_app.py
Metrik/main.py
Metrik-1.0.dist-info/METADATA
Metrik-1.0.dist-info/WHEEL
Metrik-1.0.dist-info/top_level.txt
Metrik-1.0.dist-info/RECORD
