Metadata-Version: 2.1
Name: Metrik
Version: 1.0
Requires-Dist: pyodbc
